simple_webbrowser/__init__.py
simple_webbrowser/youtube.py
simple_webbrowser-0.2.2.dist-info/METADATA
simple_webbrowser-0.2.2.dist-info/WHEEL
simple_webbrowser-0.2.2.dist-info/licenses/LICENSE
simple_webbrowser-0.2.2.dist-info/RECORD
