Metadata-Version: 2.1
Name: simple_webbrowser
Version: 0.2.2
Summary: Need something simple? Need a webbrowser? This is simple_webbrowser.
Project-URL: Homepage, https://github.com/MF366-Coding/simple_webbrowser
Project-URL: Bug Tracker, https://github.com/MF366-Coding/simple_webbrowser/issues
Author-email: MF366 <real_mf366@yahoo.com>
License-File: LICENSE
Classifier: License :: OSI Approved :: MIT License
Classifier: Operating System :: OS Independent
Classifier: Programming Language :: Python :: 3
Requires-Python: >=3.10
